{
  "last_update": "2026-03-29T16:23:19.195666",
  "generated_at": "2026-03-29T16:23:19.195666",
  "total_records": 1,
  "regiones": {
    "GLOBAL": {
      "count": 1,
      "departamentos": {
        "03._ATLANTICO": {
          "count": 1,
          "municipios": {
            "061._USIACURI": {
              "count": 1,
              "zonas": {
                "00._ZONA_0": {
                  "count": 1,
                  "puestos": {
                    "00._PUESTO_CABECERA_MUNICIPAL": {
                      "count": 1,
                      "path": "GLOBAL/03._ATLANTICO/061._USIACURI/00._ZONA_0/00._PUESTO_CABECERA_MUNICIPAL"
                    }
                  }
                }
              }
            }
          }
        }
      }
    }
  }
}